django_service_urls/__init__.py
django_service_urls/base.py
django_service_urls/exceptions.py
django_service_urls/loads.py
django_service_urls/mypy.py
django_service_urls/parse.py
django_service_urls/py.typed
django_service_urls/version.py
django_service_urls/services/__init__.py
django_service_urls/services/cache.py
django_service_urls/services/database.py
django_service_urls/services/email.py
django_service_urls/services/storages.py
django_service_urls/services/tasks.py
django_service_urls-2.1.dist-info/licenses/LICENSE
django_service_urls-2.1.dist-info/METADATA
django_service_urls-2.1.dist-info/WHEEL
django_service_urls-2.1.dist-info/top_level.txt
django_service_urls-2.1.dist-info/RECORD
