Metadata-Version: 2.4
Name: django-service-urls
Version: 2.1
Summary: setting helper for django to represent databases, caches and email settings via a single string
Author-email: Raffaele Salmaso <raffaele@salmaso.org>
License-Expression: BSD-2-Clause
Project-URL: Home Page, https://pypi.org/project/django-service-urls/
Project-URL: Documentation, https://github.com/rsalmaso/django-service-urls/blob/main/README.md
Project-URL: GitHub, https://github.com/rsalmaso/django-service-urls
Project-URL: Changelog, https://github.com/rsalmaso/django-service-urls/blob/main/CHANGELOG.md
Project-URL: Bug Reports, https://github.com/rsalmaso/django-service-urls/discussions
Classifier: Development Status :: 5 - Production/Stable
Classifier: Operating System :: OS Independent
Classifier: Environment :: Web Environment
Classifier: Programming Language :: Python
Classifier: Topic :: Internet :: WWW/HTTP
Classifier: Topic :: Internet :: WWW/HTTP :: Dynamic Content
Classifier: Topic :: Internet :: WWW/HTTP :: WSGI
Classifier: Topic :: Software Development :: Libraries :: Application Frameworks
Classifier: Topic :: Software Development :: Libraries :: Python Modules
Classifier: Framework :: Django
Classifier: Framework :: Django :: 3.2
Classifier: Framework :: Django :: 4.0
Classifier: Framework :: Django :: 4.1
Classifier: Framework :: Django :: 4.2
Classifier: Framework :: Django :: 5.0
Classifier: Framework :: Django :: 5.1
Classifier: Framework :: Django :: 5.2
Classifier: Framework :: Django :: 6.0
Classifier: Programming Language :: Python :: 3
Classifier: Programming Language :: Python :: 3.10
Classifier: Programming Language :: Python :: 3.11
Classifier: Programming Language :: Python :: 3.12
Classifier: Programming Language :: Python :: 3.13
Classifier: Programming Language :: Python :: 3.14
Requires-Python: >=3.10
License-File: LICENSE
Requires-Dist: django
Dynamic: license-file
